isl/__init__.py
isl/recompilers/__init__.py
isl/recompilers/approximate_recompiler.py
isl/recompilers/fixed_ansatz_recompiler.py
isl/recompilers/isl_recompiler.py
isl/recompilers/rotoselect_recompiler.py
isl/test/__init__.py
isl/test/test_circuit_operations.py
isl/test/test_entanglement_measures.py
isl/test/test_fixed_vqe.py
isl/test/test_isl.py
isl/test/test_qulacs.py
isl/test/test_rotoselect_recompiler.py
isl/utils/__init__.py
isl/utils/constants.py
isl/utils/cost_minimiser.py
isl/utils/entanglement_measures.py
isl/utils/fixed_ansatz_circuits.py
isl/utils/gate_tomography.py
isl/utils/hamiltonians.py
isl/utils/utilityfunctions.py
isl/utils/circuit_operations/__init__.py
isl/utils/circuit_operations/circuit_operations_alternate_emulators.py
isl/utils/circuit_operations/circuit_operations_basic.py
isl/utils/circuit_operations/circuit_operations_circuit_division.py
isl/utils/circuit_operations/circuit_operations_full_circuit.py
isl/utils/circuit_operations/circuit_operations_optimisation.py
isl/utils/circuit_operations/circuit_operations_parameterised.py
isl/utils/circuit_operations/circuit_operations_pauli_ops.py
isl/utils/circuit_operations/circuit_operations_running.py
isl/utils/circuit_operations/circuit_operations_variational.py
isl/vqe/__init__.py
isl/vqe/fixed_ansatz_vqe.py
isl/vqe/variational_quantum_eigensolver.py
quantum_isl-1.0.1.dist-info/LICENSE
quantum_isl-1.0.1.dist-info/METADATA
quantum_isl-1.0.1.dist-info/WHEEL
quantum_isl-1.0.1.dist-info/top_level.txt
quantum_isl-1.0.1.dist-info/RECORD
