Metadata-Version: 2.1
Name: quantum-isl
Version: 1.0.1
Summary: A package for implementing the Incremental         Structure Learning (ISL) algorithm for approximate             circuit recompilation
Home-page: https://github.com/abhishekagarwal2301/isl
Author: Abhishek Agarwal
Author-email: abhishek.agarwal@npl.co.uk
License: LICENSE
License-File: LICENSE
Requires-Dist: qiskit (==0.36)
Requires-Dist: numpy
Requires-Dist: scipy
Requires-Dist: openfermion (~=1.5)
